soundpad_control/__init__.py
soundpad_control/errors.py
soundpad_control/remote_control.py
soundpad_control-0.1.2.dist-info/LICENSE
soundpad_control-0.1.2.dist-info/METADATA
soundpad_control-0.1.2.dist-info/WHEEL
soundpad_control-0.1.2.dist-info/RECORD
