Metadata-Version: 2.1
Name: soundpad_control
Version: 0.1.2
Summary: An API wrapper for Soundpad written in Python.
Home-page: https://github.com/Ilya-Kokhanovsky/soundpad.py
License: MIT
Keywords: soundpad,remote control,audio
Author: Ilya Kokhanovsky
Author-email: kokhanovskyilya@gmail.com
Maintainer: Ilya Kokhanovsky
Maintainer-email: kokhanovskyilya@gmail.com
Requires-Python: >=3.6,<4.0
Classifier: License :: OSI Approved :: MIT License
Classifier: Programming Language :: Python :: 3
Classifier: Programming Language :: Python :: 3.6
Classifier: Programming Language :: Python :: 3.7
Classifier: Programming Language :: Python :: 3.8
Classifier: Programming Language :: Python :: 3.9
Classifier: Programming Language :: Python :: 3.10
Classifier: Programming Language :: Python :: 3.11
Classifier: Programming Language :: Python :: 3.12
Classifier: Programming Language :: Python :: 3.13
Project-URL: Repository, https://github.com/Ilya-Kokhanovsky/soundpad.py
